pyqt_preview/__init__.py
pyqt_preview/cli.py
pyqt_preview/compiler.py
pyqt_preview/config.py
pyqt_preview/core.py
pyqt_preview/logging_config.py
pyqt_preview/security.py
pyqt_preview/watcher.py
pyqt_preview-0.2.0.dist-info/METADATA
pyqt_preview-0.2.0.dist-info/WHEEL
pyqt_preview-0.2.0.dist-info/entry_points.txt
pyqt_preview-0.2.0.dist-info/licenses/LICENSE
pyqt_preview-0.2.0.dist-info/RECORD
