Metadata-Version: 2.4
Name: pyqt-preview
Version: 0.2.0
Summary: Live preview tool for PyQt GUI development
Project-URL: Homepage, https://github.com/Reynear/pyqt-preview
Project-URL: Repository, https://github.com/Reynear/pyqt-preview
Project-URL: Documentation, https://github.com/Reynear/pyqt-preview#readme
Project-URL: Bug Tracker, https://github.com/Reynear/pyqt-preview/issues
Author: PyQt Preview Contributors
License: MIT
License-File: LICENSE
Keywords: development,gui,live-reload,preview,pyqt
Classifier: Development Status :: 3 - Alpha
Classifier: Intended Audience :: Developers
Classifier: License :: OSI Approved :: MIT License
Classifier: Programming Language :: Python :: 3
Classifier: Programming Language :: Python :: 3.9
Classifier: Programming Language :: Python :: 3.10
Classifier: Programming Language :: Python :: 3.11
Classifier: Programming Language :: Python :: 3.12
Classifier: Programming Language :: Python :: 3.13
Classifier: Topic :: Software Development :: Libraries :: Python Modules
Classifier: Topic :: Software Development :: User Interfaces
Requires-Python: >=3.9
Requires-Dist: rich>=13.8.0
Requires-Dist: tomli>=2.0.0; python_version < '3.11'
Requires-Dist: typer>=0.12.0
Requires-Dist: watchdog>=4.0.0
Provides-Extra: build
Requires-Dist: hatch>=1.9.0; extra == 'build'
Requires-Dist: twine>=5.0.0; extra == 'build'
Provides-Extra: dev
Requires-Dist: bandit[toml]>=1.7.10; extra == 'dev'
Requires-Dist: hatch>=1.9.0; extra == 'dev'
Requires-Dist: mypy>=1.13.0; extra == 'dev'
Requires-Dist: pre-commit>=4.0.0; extra == 'dev'
Requires-Dist: pytest-cov>=5.0.0; extra == 'dev'
Requires-Dist: pytest>=8.3.0; extra == 'dev'
Requires-Dist: ruff>=0.8.0; extra == 'dev'
Provides-Extra: pyqt5
Requires-Dist: pyqt5>=5.15.11; extra == 'pyqt5'
Provides-Extra: pyqt6
Requires-Dist: pyqt6>=6.7.0; extra == 'pyqt6'
Provides-Extra: pyside2
Requires-Dist: pyside2>=5.15.2; extra == 'pyside2'
Provides-Extra: pyside6
Requires-Dist: pyside6>=6.8.0; extra == 'pyside6'
Provides-Extra: test
Requires-Dist: pytest-cov>=5.0.0; extra == 'test'
Requires-Dist: pytest>=8.3.0; extra == 'test'
